__init__.py
constants.py
d8fmt.py
d8fmt-0.5.0.dist-info/METADATA
d8fmt-0.5.0.dist-info/WHEEL
d8fmt-0.5.0.dist-info/entry_points.txt
d8fmt-0.5.0.dist-info/top_level.txt
d8fmt-0.5.0.dist-info/RECORD
