Metadata-Version: 2.4
Name: d8fmt
Version: 0.5.0
Summary: Add your description here
Requires-Python: >=3.13
Requires-Dist: coverage==7.10.4
Requires-Dist: pytest==8.4.1
